[
    {
        "name": "Torsk med chorizosalsa, brokkoli og søtpotetmos",
        "categories": ["Hvit fisk"],
        "approach": [
            "Kok søtpotet. Hell av mesteparten av vannet. Mos så med stavmikser. Varm opp mosen sammen med litt melk/fløte og smak til med krydder.",
            "Rist pinjekjernene i en tørr stekepanne og legg til side. Stek deretter Chorizo, 1 sjalottløk og 1 fedd hvitløk. Tilsett pinjekjernene og litt sitronsaft før servering.",
            "Skyll torskefiltene og tørk med tørkepapir. Pensle med sitronsaft, olje, salt og pepper. Stek i panne i ca. 3 minutter på hver side til den flaker seg.", 
            "Koke asparges i ca. 2 minutter i vann tilsatt litt salt og sukker.",
            "Server evt med potet bakt i ovnen med olje, salt og pepper."
        ],
        "ingredients": [
            {    
                "name": "Torsk",
                "amount": 3,
                "unit": "filter",
                "category": "fisk"
            },
            {    
                "name": "Brokkoli",
                "amount": 1,
                "unit": "stk",
                "category": "grønnsaker"
            },
            {    
                "name": "Søtpotet",
                "amount": 1,
                "unit": "stk",
                "category": "grønnsaker"
            },
            {    
                "name": "Sjalottløk",
                "amount": 1,
                "unit": "stk",
                "category": "grønnsaker"
            },
            {    
                "name": "Hvitløk",
                "amount": 1,
                "unit": "fedd",
                "category": "grønnsaker"
            },
            {    
                "name": "Sitronsaft",
                "amount": 0,
                "unit": "",
                "category": "annet"
            },
            {    
                "name": "Chorizo",
                "amount": 1,
                "unit": "pakke",
                "category": "kjøtt"
            },
            {    
                "name": "Matfløte",
                "amount": 0.5,
                "unit": "dl",
                "category": "meieri"
            }           
        ]
    },
    {
        "name": "Sei med soppstuing",
        "categories": ["Hvit fisk"],
        "approach": [
            "Sett poteter på kok, og kutt opp og kok gullrøtter og blomkål.", 
            "Kutt og stek sopp og bacon. Krydre med salt og pepper.",
            "Bland 2 dl creme fraich inn i soppen og baconet.", 
            "Stek seien."
        ],
        "ingredients": [
            {    
                "name": "Sei",
                "amount": 400,
                "unit": "g",
                "category": "fisk"
            },
            {    
                "name": "Sopp",
                "amount": 500,
                "unit": "g",
                "category": "grønnsaker"
            },
            {    
                "name": "Bacon",
                "amount": 100,
                "unit": "g",
                "category": "kjøtt"
            },
            {    
                "name": "Creme fraiche",
                "amount": 2,
                "unit": "dl",
                "category": "meieri"
            },
            {    
                "name": "Potet",
                "amount": 600,
                "unit": "g",
                "category": "grønnsaker"
            },
            {    
                "name": "Gulrot",
                "amount": 1,
                "unit": "stk",
                "category": "grønnsaker"
            },
            {    
                "name": "Blomkål",
                "amount": 0.5,
                "unit": "stk",
                "category": "grønnsaker"
            }
        ]
    },
    {
        "name": "Sei med sopp og ris",
        "categories": ["Hvit fisk"],
        "approach": [
            "Kok ris.",
            "Kutt og stek soppen.",
            "Krydre seien med salt og pepper. Stek i en panne, og mos noe.",
            "Rist sammen 3dl matfløte med en spiseskje mel i et syltetøyglass. ",
            "Ha fløten over soppen og bland inn seien."
        ],
        "ingredients": [
            {    
                "name": "Sei",
                "amount": 400,
                "unit": "g",
                "category": "fisk"
            },
            {    
                "name": "Sopp",
                "amount": 500,
                "unit": "g",
                "category": "grønnsaker"
            },
            {    
                "name": "Ris",
                "amount": 0,
                "unit": "",
                "category": "annet"
            },
            {    
                "name": "Matfløte",
                "amount": 3,
                "unit": "dl",
                "category": "grønnsaker"
            }
        ]
    },
    
    {
        "name": "Ingefærsei med eple og karrisaus",
        "categories": ["Hvit fisk"],
        "approach": [
            "Sett stekeovnen på 200 grader, sett over poteter og vann til asparges.",
            "Bland sammen ingrediensene til sausen (rømme, eple, karri, salt og pepper).",
            "Krydre seien med salt og pepper og legg dem i en ildfast form. Skrell og riv ingefær, bland med olje og soyasaus. Fordel blandingen over seistykkene. Dekk formen med aluminiumsfolie og stek i ca 15. minutter til fisken så vidt flaker seg.",
            "Rens asparges. Knekk av den nederste delen av aspargesen og kok dem i lettsaltet vann i 2-3 minutter.",
            "Server seien med eple-og-karri-sausen, poteter og asparges."
        ],
        "ingredients": [
            {    
                "name": "Sei",
                "amount": 400,
                "unit": "g",
                "category": "fisk"
            },
            {    
                "name": "Eple",
                "amount": 1,
                "unit": "stk",
                "category": "grønnsaker"
            },
            {    
                "name": "Ingefær",
                "amount": 2,
                "unit": "ss",
                "category": "grønnsaker"
            },
            {    
                "name": "Rømme",
                "amount": 3,
                "unit": "dl",
                "category": "meieri"
            },
            {
                "name": "Soyasaus",
                "amount": 4,
                "unit": "ss",
                "category": "annet"
            },
            {    
                "name": "Brokkoli",
                "amount": 1,
                "unit": "stk",
                "category": "grønnsaker"
            },
            {    
                "name": "Potet",
                "amount": 600,
                "unit": "g",
                "category": "grønnsaker"
            }
        ]
    },
    {
        "name": "Hvit fisk med eplesmørsaus",
        "categories": ["Hvit fisk"],
        "approach": [
            "Tilbered potet etter ønske",
            "Tørk av fisken og krydre den med salt og pepper",
            "Skrell og kutt opp grønnsaker.",
            "Skrell og finhakk sjalottløk og hvitløk. Du kan dele opp eplet i små terninger allerede nå, men bland i litt sitron slik at bitene ikke blir brune.",
            "Varm opp olje i en stekepanne. Ha i smøret og stek fisken cirka 3-4 minutter på hver side. La hvile av varmen når den er ferdigstekt.",
            "De neste stegene er til eplesmørsausen:",
            "Kok sjalottløk og hvitløk sammen med eplejuicen i en liten kasserolle, til den er redusert til halvparten. Sil væsken, tilsett kremfløten og la den koke videre til den har tyknet en del.",
            "Dra kasserollen av varmen og visp inn terninger av kaldt smør. Smak til med sitronsaft, salt og pepper.",
            "Rett før servering rører du inn epleterninger i eplesmørsausen."
        ],
        "ingredients": [
            {    
                "name": "Hvit fisk",
                "amount": 500,
                "unit": "g",
                "category": "fisk"
            },
            {    
                "name": "Potet",
                "amount": 600,
                "unit": "g",
                "category": "grønnsaker"
            },
            {    
                "name": "Sjalottløk",
                "amount": 1,
                "unit": "stk",
                "category": "grønnsaker"
            },
            {    
                "name": "Hvitløk",
                "amount": 1,
                "unit": "fedd",
                "category": "grønnsaker"
            },
            {    
                "name": "Eplejuice",
                "amount": 1.5,
                "unit": "dl",
                "category": "annet"
            },
            {    
                "name": "Kremfløte",
                "amount": 2,
                "unit": "dl",
                "category": "meieri"
            },
            {    
                "name": "Smør",
                "amount": 25,
                "unit": "g",
                "category": "meieri"
            },
            {    
                "name": "Sitronsaft",
                "amount": 0.5,
                "unit": "ss",
                "category": "annet"
            },
            {    
                "name": "Eple",
                "amount": 1,
                "unit": "stk",
                "category": "grønnsaker"
            },
            {
                "name": "Granateple",
                "amount": 1,
                "unit": "stk",
                "category": "grønnsaker"
            }
        ]
    },
    
    {
        "name": "Soyamarinert laks",
        "categories": ["Enkel", "Rød fisk"],
        "approach": [
            "Kok ris til 3 porsjoner.",
            "Lag soyamarinade av soyasaus, sitronsaft, honning, hvitløk og chili.",
            "Stek laksen i en panne. Etter hvert tilsettes marinaden og laksen vendes i denne til den er gjennomstekt.",
            "I en annen panne stekes rødløk, paprika og ris tilsettes når den er ferdig kokt."
        ],
        "ingredients": [
            {    
                "name": "Ris",
                "amount": 0,
                "unit": "",
                "category": "annet"
            },
            {    
                "name": "Laks",
                "amount": 2,
                "unit": "fileter",
                "category": "fisk"
            },
            {    
                "name": "Soyasaus",
                "amount": 0.5,
                "unit": "dl",
                "category": "annet"
            },
            {    
                "name": "Hvitløk",
                "amount": 2,
                "unit": "fedd",
                "category": "grønnsaker"
            },
            {    
                "name": "Chili",
                "amount": 0.5,
                "unit": "stk",
                "category": "grønnsaker"
            },
            {    
                "name": "Paprika",
                "amount": 1,
                "unit": "stk",
                "category": "grønnsaker"
            },
            {    
                "name": "Rødløk",
                "amount": 1,
                "unit": "stk",
                "category": "grønnsaker"
            },
            {    
                "name": "Honning",
                "amount": 2,
                "unit": "ss",
                "category": "annet"
            },
            {    
                "name": "Sitronsaft",
                "amount": 0.5,
                "unit": "ss",
                "category": "annet"
            }
        ]
    },
    {
        "name": "Ovnsbakt laks med rød pesto",
        "categories": ["Rød fisk"],
        "approach": [
            "Sett stekeovnen på 200 grader over- og undervarme. Skjær opp grønnsakene og kok ris, poteter eller annet tilbehør etter anvisningen. ",
            "Stek løken i litt nøytral olje til den er blank og myk. La paprika og hvitløk steke med de siste minuttene. Tilsett deretter spinat og tomater og la de surre med til spinaten begynner å falle sammen. Krydre med litt salt og sort pepper. Fordel grønnsakene i en form. ",
            "Hell matfløten i stekepannen og varm opp mot kokepunktet. Tilsett en god neve ost og smak til med rød pesto, chiliflak, buljong, salt og pepper. Hell den varme sausen over grønnsakene.",
            "Krydre laksen med litt salt og dytt dem litt nedi grønnsaksblandingen. Rør sammen persille, 2 ss ost, pinjekjerner, sitronsaft og olivenolje, og smak til med salt og pepper. Fordel blandingen oppå fisken.",
            "Stekes på midterste rille i ca. 18 minutter, til fisken er passe stekt og nøttelokket har tatt litt farge. "

        ],
        "ingredients": [
            {
                "name": "Persille",
                "amount": 3,
                "unit": "ss",
                "category": "grønnsaker"
            },
            {    
                "name": "Laks",
                "amount": 2,
                "unit": "fileter",
                "category": "fisk"
            },
            {    
                "name": "Rød pesto",
                "amount": 3,
                "unit": "ts",
                "category": "annet"
            },
            {    
                "name": "Rødløk",
                "amount": 1,
                "unit": "stk",
                "category": "grønnsaker"
            },
            {    
                "name": "Paprika",
                "amount": 1,
                "unit": "stk",
                "category": "grønnsaker"
            },
            {    
                "name": "Cherrytomat",
                "amount": 50,
                "unit": "g",
                "category": "grønnsaker"
            },
            {    
                "name": "Potet",
                "amount": 600,
                "unit": "g",
                "category": "grønnsaker"
            },
            {    
                "name": "Hvitløk",
                "amount": 2,
                "unit": "fedd",
                "category": "grønnsaker"
            },
            {    
                "name": "Matfløte",
                "amount": 1.5,
                "unit": "dl",
                "category": "meieri"
            },
            {    
                "name": "Ost",
                "amount": 0,
                "unit": "",
                "category": "meieri"
            },
            {    
                "name": "Sitronsaft",
                "amount": 0,
                "unit": "",
                "category": "annet"
            },
            {    
                "name": "Pinjekjerner",
                "amount": 2,
                "unit": "ss",
                "category": "annet"
            }
        ]
    },
    {
        "name": "Laks med vårløk og sukkererter",
        "categories": ["Rød fisk", "Enkel"],
        "approach": [
            "Start med å finne frem en stekepanne og sett på høy varme. Legg i smøret. ",
            "Skyll og kut vårløken. Stek i noen minutter til vårløken blir myk. ",
            "Hell i 1 dl vann blandet med 4ss hvitvinseddik og la dette nesten koke bort.",
            "Ha i grovkuttede sukkererter og hell over fløten. Legg i 2 ss sennep og bland sammen. La denne blandingen koke i 5-8 minutter til fløten begynner å tykne. ",
            "Legg i laksen og dekk til med lokk eller aluminiumsfolie.",
            "Skru ned varmen til medium/lav og vent i 5 minutter. Ta av folien/lokket og smak til med salt og pepper. ",
            "Evt: Hell over granateplekjerner "
        ],
        "ingredients": [
            {    
                "name": "Laks",
                "amount": 2,
                "unit": "fileter",
                "category": "fisk"
            },
            {    
                "name": "Vårløk",
                "amount": 1,
                "unit": "bunt",
                "category": "grønnsaker"
            },
            {    
                "name": "Sukkererter",
                "amount": 100,
                "unit": "g",
                "category": "grønnsaker"
            },
            {    
                "name": "Potet",
                "amount": 600,
                "unit": "g",
                "category": "grønnsaker"
            },
            {    
                "name": "Smør",
                "amount": 1,
                "unit": "ss",
                "category": "meieri"
            },
            {    
                "name": "Hvitvinseddik",
                "amount": 4,
                "unit": "ss",
                "category": "annet"
            },
            {    
                "name": "Kremfløte",
                "amount": 2.5,
                "unit": "dl",
                "category": "meieri"
            },
            {    
                "name": "Sennep",
                "amount": 2,
                "unit": "ss",
                "category": "annet"
            }
        ]
    },
    {
        "name": "Prinsessegryte",
        "categories": ["Rød fisk", "Enkel"],
        "approach": [
            "Fres finhakket sjalottløk, hvitløk og chili i litt olje. Tilsett 2 dl vann og hønsebuljong og la småkoke i noen minutter. ",
            "Tilsett melk, creme fraiche og revet parmesan. La det småkoke litt før du tilsetter den rå fisken, skåret i terninger.",
            "Skru ned varmen og la fisken trekke i 5-10 minutter. ",
            "Smak til med salt, pepper og fersk basilikum."
        ],
        "ingredients":[
            {
                "name": "Laks",
                "amount": 3,
                "unit": "fileter",
                "category": "fisk"
            },
            {
                "name": "Chili",
                "amount": 0.5,
                "unit": "stk",
                "category": "grønnsaker"
            },
            {
                "name": "Hvitløk",
                "amount": 1,
                "unit": "fedd",
                "category": "grønnsaker"
            },
            {
                "name": "Craime fraiche",
                "amount": 4,
                "unit": "ss",
                "category": "meieri"
            },
            {
                "name": "Parmasan",
                "amount": 60,
                "unit": "g",
                "category": "meieri"
            },
            {
                "name": "Melk",
                "amount": 0.5,
                "unit": "dl",
                "category": "meieri"
            }
        ]
    },
    {
        "name": "Hot kyllingsuppe",
        "categories": ["Kylling", "Suppe"],
        "approach": [
            "Del kyllingfilet i biter, skrell og del eple i mindre biter og finhakk løk.",
            "Smelt smør med karri i en kjele.",
            "Brun kyllingbiter raskt og sett til side.",
            "Fres eple og løk i smør og tilsett vann, tomater, buljongterning, matfløte og sukker. Kok opp og la småkoke i 5–10 minutter. Smak til med salt og pepper.",
            "Kan sløyfes: Bland Snøfrisk og lettrømme til en jevn krem. Server suppen toppet med ostekrem, stekt kylling og et dryss av friske urter."
        ],
        "ingredients": [
            {
                "name": "Kyllingfilet",
                "amount": 2,
                "unit": "fileter",
                "category": "kjøtt"
            },
            {
                "name": "Eple",
                "amount": 1,
                "unit": "stk",
                "category": "grønnsaker"
            },
            {
                "name": "Løk",
                "amount": 1,
                "unit": "stk",
                "category": "grønnsaker"
            },
            {
                "name": "Smør",
                "amount": 2,
                "unit": "ss",
                "category": "meieri"
            },
            {
                "name": "Karri",
                "amount": 1,
                "unit": "ss",
                "category": "annet"
            },
            {
                "name": "Hakka tomater",
                "amount": 2,
                "unit": "boks",
                "category": "annet"
            },
            {
                "name": "Buljong",
                "amount": 2,
                "unit": "stk",
                "category": "annet"
            },
            {
                "name": "Matfløte",
                "amount": 3,
                "unit": "dl",
                "category": "meieri"
            }
        ]
    },
    {
        "name": "Pastapanne med kylling og bacon",
        "categories": ["Kylling", "Pasta"],
        "approach": [
            "Kok pasta etter anvisning på pakken i lettsaltet vann. Vask og kutt tomat i terninger og finhakk hvitløk.",
            "Sprøstek bacon på middels høy varme i en stekepanne. Del i terninger og legg til side. ",
            "Krydre kyllingfiletene med salt, pepper, paprikakrydder og oregano. Hell av overflødig baconfett fra stekepannen, og stek filetene på middels varme til de er gjennomstekt. Ta kyllingen ut av pannen og del i skiver.",
            "Legg skivene tilbake i pannen og tilsett terninger av tomat, spinat, finhakket hvitløk og halvparten av baconterningene. Bland godt.",
            "Tilsett fløte og kok på middels varme i noen minutter før du tilsetter revet ost. Skru ned varmen og la det putre i ca. 2-3 minutter. Ta av platen og bland inn ferdigkokt pasta.",
            "Server pastapanne med kylling, bacon og spinat. Topp med resten av baconterningene og chiliflak."
            
        ],
        "ingredients": [
            {
                "name": "Kyllingfilet",
                "amount": 2,
                "unit": "fileter",
                "category": "kjøtt"
            },
            {
                "name": "Bacon",
                "amount": 180,
                "unit": "g",
                "category": "kjøtt"
            },
            {
                "name": "Pasta penne", 
                "amount": 400,
                "unit": "g",
                "category": "annet"
            },
            {
                "Name": "Kremfløte", 
                "amount": 2,
                "unit": "dl",
                "category": "meieri"
            },
            {
                "name": "Ost",
                "amount": 150,
                "unit": "g",
                "category": "meieri"
            },
            {
                "name": "Tomat",
                "amount": 3,
                "unit": "stk",
                "category": "grønnsaker"
            },
            {
                "name": "Hvitløk",
                "amount": 2,
                "unit": "fedd",
                "category": "grønnsaker"
            },
            {
                "name": "Spinat",
                "amount": 100,
                "unit": "g",
                "category": "grønnsaker"
            }
        ]
    },
    {
        "name": "Pasta carbonara",
        "categories": ["Pasta"],
        "approach": [
            "Skjær brokkoli og bacon i små biter og stek i en romslig stekepanne med litt olivenolje.  Sett pannen til side så lenge.",
            "Visp egg og ost godt sammen i en bolle, til blandingen blir litt luftig.",
            "Kok pastaen i rikelig, fosskokende, godt saltet vann (bruk cirka 1 ss salt per liter). Husk at pastaen skal kokes «al dente», det vil si at det fortsatt skal være litt tyggemotstand i pastaen. Ta vare på cirka 1 ½ dl av kokevannet når du heller den perfekt kokte pastaen over i et dørslag.",
            "Gi pannen med bacon og brokkoli en rask oppvarming før du trekker pannen til side og heller all pastaen over i pannen. Tilsett eggeblandingen og spe med litt av kokevannet mens du svinger på pannen og blander alt godt sammen. Sausen skal bli saftig, glatt og glinsende - og absolutt ikke kornete. ",
            "Krydre med kvernet sort pepper og salt hvis nødvendig.",
            "Serveres umiddelbart med litt ekstra parmesan eller pecorino!"
        ],
        "ingredients": [
            {
                "name": "Bacon",
                "amount": 100,
                "unit": "g",
                "category": "kjøtt"
            },
            {
                "name": "Parmesan",
                "amount": 50,
                "unit": "g",
                "category": "meieri"
            },
            {
                "name": "Egg",
                "amount": 2,
                "unit": "stk",
                "category": "annet"
            },
            {
                "name": "Tagliatelle",
                "amount": 200,
                "unit": "g",
                "category": "annet"
            },
            {
                "name": "Brokkoli",
                "amount": 1,
                "unit": "stk",
                "category": "grønnsaker"
            }
        ]
    },
    {
        "name": "Pasta med kylling og pesto",
        "categories": ["Kylling", "Pasta"],
        "approach": [
            "Kok pasta etter anvisning på pakken. ",
            "Stek kyllingfilet i en panne med olje, salt og pepper. ",
            "Stek eller kok brokkoli. ",
            "Bland sammen pasta, kylling, brokkoli og pesto. Server gjerne med litt revet parmesan."
        ],
        "ingredients": [
            {
                "name": "Kyllingfilet",
                "amount": 2,
                "unit": "fileter",
                "category": "kjøtt"
            },
            {
                "name": "Pesto",
                "amount": 2,
                "unit": "ss",
                "category": "annet"
            },
            {
                "name": "Pasta",
                "amount": 200,
                "unit": "g",
                "category": "annet"
            },
            {
                "name": "Brokkoli",
                "amount": 1,
                "unit": "stk",
                "category": "grønnsaker"
            }
        ]
    },
    {
        "name": "Kyllinggryte med soltørkede tomater",
        "categories": ["Kylling", "Rester"],
        "approach": [
            "Hell av det øverste laget av olje fra glasset med tomatene. Legg resten av innholdet sammen med hakket hvitløk i en gryte. La dette frese noen minutter før du tilsetter fløte, soyasaus og hønsebuljong. La dette småkoke en stund.",
            "Klipp kyllingfiletene opp i små biter som du har oppi gryta helt rå. Nå må retten småkoke i minst 30 minutter før du smaker til med pepper og fersk basilikum like før servering.",
            "Som tilbehør kan en koke ris og lage en frisk salat av cherrytomat, agurk og fetaost, gjerne med litt olje, salt og pepper. Rundstykker eller foccaciabrød passer også godt til."
            
        ],
        "ingredients":[
            {
                "name": "Kyllingfilet",
                "amount": 4,
                "unit": "fileter",
                "category": "kjøtt"
            },
            {
                "name": "Soyasaus",
                "amount": 2,
                "unit": "ss",
                "category": "annet"
            },
            {
                "name": "Hvitløk",
                "amount": 2,
                "unit": "fedd",
                "category": "grønnsaker"
            },
            {
                "name": "Soltørkede tomater",
                "amount": 1,
                "unit": "glass",
                "category": "grønnsaker"
            },
            {
                "name": "Matfløte",
                "amount": 6,
                "unit": "dl",
                "category": "meieri"
            },
            {
                "name": "Ris",
                "amount": 0,
                "unit": "",
                "category": "annet"
            },
            {
                "name": "Salat",
                "amount": 0.3,
                "unit": "stk",
                "category": "grønnsaker"
            },
            {
                "name": "Paprika",
                "amount": 1,
                "unit": "stk",
                "category": "grønnsaker"
            },
            {
                "name": "Agurk",
                "amount": 0.3,
                "unit": "stk",
                "category": "grønnsaker"
            },
            {
                "name": "Tomat",
                "amount": 2,
                "unit": "stk",
                "category": "grønnsaker"
            },
            {
                "name": "Fetaost",
                "amount": 1,
                "unit": "glass",
                "category": "annet"
            }
        ]
    },
    {
        "name": "Enkel kyllingwok",
        "categories": ["Kylling", "Enkel", "Asiatisk"],
        "approach": [
            "Kutt opp kyllingen og stek i en stor panne (for å få plass til resten i samme panne til slutt)",
            "Kok nudlene",
            "Skru opp varmen på stekepannen og wok grønnsakene",
            "Tilsett wok saus og nudlene. Klipp evt. nudlene for å få de mer innblandet i det andre."
        ],
        "ingredients": [
            {
                "name": "Kyllingfilet",
                "amount": 2,
                "unit": "fileter",
                "category": "kjøtt"
            },
            {
                "name": "Wokgrønnsaker",
                "amount": 1,
                "unit": "pose",
                "category": "grønnsaker"
            },
            {
                "name": "Nudler",
                "amount": 3,
                "unit": "pakker",
                "category": "annet"
            },
            {
                "name": "Woksaus",
                "amount": 1,
                "unit": "valgfri",
                "category": "annet"
            }
        ]
    }, 
    {
        "name": "Tortilla med kylling, grønnsaker og youghurtdressing",
        "categories": ["Kylling", "Enkel"],
        "approach": [
            "Kutt kyllingfileter i biter. Stek og krydre med salt og pepper.",
            "Kutt og stek grønnsakene. (evt. bruk frossen wok-mix.)",
            "Bland sammen yoghurt og Sweet chili saus.",
            "Varm lefsene."
        ],
        "ingredients": [
            {
                "name": "Kyllingfilet",
                "amount": 2,
                "unit": "fileter",
                "category": "kjøtt"
            },
            {
                "name": "Tortilla",
                "amount": 4,
                "unit": "stk",
                "category": "annet"
            },
            {
                "name": "Sweet chilisaus",
                "amount": 0,
                "unit": "",
                "category": "annet"
            },
            {
                "name": "Wokgrønnsaker",
                "amount": 1,
                "unit": "pose",
                "category": "grønnsaker"
            },
            {
                "name": "Youghurt naturell",
                "amount": 1,
                "unit": "boks",
                "category": "meieri"
            }
        ]
    },
    {
        "name": "Kylling i mangochutney",
        "categories": ["Lørdagsmat", "Rester"],
        "approach": [
            "Gjennomstek kyllingfiletene med litt salt og pepper.",
            "Saus: Visp fløten til krem. Bland inn hakket hvitløk, sambal oelek/chilipasta og karri under vispingen. Bland til slutt inn mangochutneyen med en slikkepott.",
            "Grønnsaker: Kutt løk, paprika og mango i store biter og legg grønnsakene i en ildfast form.",
            "Legg kyllingfiletene oppå grønnsakene, og hell over kremsausen.",
            "Stek i ovn på 180 grader i 30 minutter."
            
        ],
        "ingredients": [
            {
                "name": "Kyllingfilet",
                "amount": 4,
                "unit": "fileter",
                "category": "kjøtt"
            },
            {
                "name": "Mangochutney",
                "amount": 1,
                "unit": "glass",
                "category": "annet"
            },
            {
                "name": "Ris",
                "amount": 0,
                "unit": "",
                "category": "annet"
            },
            {
                "name": "Hvitløk",
                "amount": 2,
                "unit": "fedd",
                "category": "grønnsaker"
            },
            {
                "name": "Paprika",
                "amount": 2,
                "unit": "stk",
                "category": "grønnsaker"
            },
            {
                "name": "Løk",
                "amount": 2,
                "unit": "stk",
                "category": "grønnsaker"
            },
            {
                "name": "Mango",
                "amount": 1,
                "unit": "stk",
                "category": "grønnsaker"
            },
            {
                "name": "Samba oelek",
                "amount": 2,
                "unit": "ts",
                "category": "annet"
            },
            {
                "name": "Kremfløte",
                "amount": 3,
                "unit": "dl",
                "category": "meieri"
            },
            {
                "name": "Karri",
                "amount": 2,
                "unit": "ts",
                "category": "annet"
            }
        ]
    },
    {
        "name": "Kylling med bacon og kremost", 
        "categories": ["Kylling"],
        "approach": [
            "Kutt og krydre potetene med salt og pepper. Stek i ovnen.",
            "Forstek kyllingen noe i pannen.",
            "Legg på en klatt kremost på hver kyllingbit og surr bacon rundt.",
            "Kutt opp squash og legg i en ildfast form. ",
            "Legg den surrede kyllingen over og stek i ovnen."
            
        ],
        "ingredients": [
            {
                "name": "Kyllingfilet",
                "amount": 2,
                "unit": "fileter",
                "category": "kjøtt"
            },
            {
                "name": "Bacon",
                "amount": 100,
                "unit": "g",
                "category": "kjøtt"
            },
            {
                "name": "Kremost",
                "amount": 1,
                "unit": "boks",
                "category": "meieri"
            },
            {
                "name": "Hvitløk",
                "amount": 2,
                "unit": "fedd",
                "category": "grønnsaker"
            },
            {
                "name": "Sqush",
                "amount": 1,
                "unit": "stk",
                "category": "grønnsaker"
            },
            {
                "name": "Potet",
                "amount": 600,
                "unit": "g",
                "category": "grønnsaker"
            }
        ]
    },
    {
        "name": "Kremet baconpasta",
        "categories": ["Pasta"],
        "approach": [
            "Stek baconet sakte på lav varme til det er sprøtt på begge sider. Ta ut og sett til side på en tallerken med tørkepapir. Reserver 1 ss baconfett. Fjern eventuelle svarte flekker fra pannen, men la de brune restene ligge på bunnen, da dette vil gi god smak til sausen.",
            "Tilsett reserverte baconfettet i pannen sammen med hvitløken på middels varme.",
            "Tilsett en skvett kyllingbuljong og bruk en silikonspatel til å 'rense' bunnen av pannen. Fortsett å tilsette små skvetter buljong mens hvitløken steker i 1-2 minutter.",
            "Når bunnen og sidene av pannen er rene, vil du sitte igjen med en brun væske full av smak. Tilsett eventuell gjenværende kyllingbuljong sammen med tomatpuré, krydder og «tung fløte». Rør for å blande. Kok opp, og reduser så varmen.",
            "Tilsett cherrytomater, rød pepperflak og romtemperert kremost. Rør for å blande kremosten i sausen. Dekk til delvis og la det boble litt mens du begynner å koke saltet pastavann. Tomatene vil til slutt dele seg.",
            "Kok pasta 1 minutt mindre enn anvist på pakken. Når pastaen er nesten ferdig, reduser varmen på sausen til lav. Dryss gradvis på nyrevet parmesanost og rør sammen. Hvis bunnen er for varm når du gjør dette, vil meieriet skille seg og du vil ha en kornete konsistens, så sørg for å la varmen reduseres til lav.",
            "Tilsette pastaen i sausen og bland sammen til ønsket saus/pasta-forhold er oppnådd. La det koke i 1 minutt til for å la sausen tykne ytterligere og for at pastaen skal absorbere den.",
            "Sausen vil fortsette å tykne ytterligere når den står. Pynt med hakket bacon og fersk persille og server med hvitløksbrød."
            
        ],
        "ingredients": [
            {
                "name": "Bacon",
                "amount": 3,
                "unit": "skiver",
                "category": "kjøtt"
            },
            {
                "name": "Hvitløk",
                "amount": 2,
                "unit": "fedd",
                "category": "grønnsaker"
            },
            {
                "name": "Kyllingbuljong",
                "amount": 1,
                "unit": "stk",
                "category": "annet"
            },
            {
                "name": "Tomatpure",
                "amount": 1,
                "unit": "ss",
                "category": "annet"
            },
            {
                "name": "Matfløte",
                "amount": 2.5,
                "unit": "dl",
                "category": "meieri"
            },
            {
                "name": "Cherrytomater",
                "amount": 200,
                "unit": "g",
                "category": "grønnsaker"
            },
            {
                "name": "Kremost",
                "amount": 1,
                "unit": "ss",
                "category": "meieri"
            },
            {
                "name": "Parmesan",
                "amount": 0.25,
                "unit": "dl",
                "category": "meieri"
            },
            {
                "name": "Spaghetti",
                "amount": 100,
                "unit": "g",
                "category": "annet"
            }        
        ]
    },
    {
        "name": "Kremet pasta i panne med skine og tomat",
        "categories": ["Enkel", "Pasta"],
        "approach": [
            "Kok pasta etter anvisningen på pakken. ",
            "Kutt 1 paprika, 6-7 sopp og 2 rødløk i passe store biter. Stek noen minutter på middels varme i en stekepanne.",
            "Skjær ca. 200g skinke i strimler. Ha den deretter i stekepannen sammen med grønnsakene. Stekes i noen minutter.",
            "Tilsett 3 ss tomatpuré og la frese litt i pannen. Ha i 1 boks crème fraîche, 1,5 dl vann, 1 terning buljong, 2 fedd hvitløk og 1 ss karri.",
            "La dette koke i noen minutter, og ha i ferdig kokt pasta mot slutten av koketiden slik at den varmes opp."
            
        ],
        "ingredients":[
            {
                "name": "Pasta",
                "amount": 300,
                "unit": "g",
                "category": "annet"
            },
            {
                "name": "Skinke",
                "amount": 200,
                "unit": "g",
                "category": "kjøtt"
            },
            {
                "name": "Hvitløk",
                "amount": 2,
                "unit": "fedd",
                "category": "grønnsaker"
            },
            {
                "name": "Rødløk",
                "amount": 2,
                "unit": "stk",
                "category": "grønnsaker"
            },
            {
                "name": "Paprika",
                "amount": 1,
                "unit": "stk",
                "category": "grønnsaker"
            },
            {
                "name": "Craime fraiche",
                "amount": 3,
                "unit": "dl",
                "category": "meieri"
            },
            {
                "name": "Tomatpurre",
                "amount": 3,
                "unit": "ss",
                "category": "annet"
            },
            {
                "name": "Sjampinjong",
                "amount": 7,
                "unit": "stk",
                "category": "grønnsaker"
            },
            {
                "name": "Matfløte",
                "amount": 2,
                "unit": "dl",
                "category": "meieri"
            },
            {
                "name": "Parmesan",
                "amount": 50,
                "unit": "g",
                "category": "meieri"
            }
        ]
    },
    {
        "name": "Enchiladas",
        "categories": ["Enkel", "Lørdagsmat", "Kylling"],
        "approach": [
            "Sett ovnen på 200 °C. Skjær kylling, paprika og løk i strimler. Varm en panne med smør og stek alt sammen med taco- eller enchiladas-krydder.",
            "Fyll hver tortilla med kyllingblandingen og rull den forsiktig sammen.",
            "Legg tortillaene i en ildfast form og topp med revet cheddar. Stek i ovnen i ca. 10 min til osten smelter. Topp med finhakket vårløk, rød chili, koriander og avokado i skiver ved servering."
            
        ],
        "ingredients":[
            {
                "name": "Kyllingfilet",
                "amount": 200,
                "unit": "g",
                "category": "kjøtt"
            },
            {
                "name": "Rødløk",
                "amount": 1,
                "unit": "stk",
                "category": "grønnsaker"
            },
            {
                "name": "Paprika",
                "amount": 1,
                "unit": "stk",
                "category": "grønnsaker"
            },
            {
                "name": "Ost",
                "amount": 75,
                "unit": "g",
                "category": "meieri"
            },
            {
                "name": "Tacokrydder",
                "amount": 0.5,
                "unit": "pose",
                "category": "annet"
            },
            {
                "name": "Tortillalefser",
                "amount": 4,
                "unit": "stk",
                "category": "annet"
            },
            {
                "name": "Avokado",
                "amount": 0.5,
                "unit": "stk",
                "category": "grønnsaker"
            },
            {
                "name": "Koriander",
                "amount": 0.5,
                "unit": "potte",
                "category": "grønnsaker"
            },
            {
                "name": "Vårløk",
                "amount": 1,
                "unit": "stk",
                "category": "grønnsaker"
            },
            {
                "name": "Chili",
                "amount": 0.5,
                "unit": "stk",
                "category": "grønnsaker"
            },
            {
                "name": "Avokado",
                "amount": 0.5,
                "unit": "stk",
                "category": "grønnsaker"
            }
        ]
    },
    {
        "name": "Stekt ris",
        "categories": ["Enkel", "Rester", "Pølse"],
        "approach": [
"Mangler."
        ],
        "ingredients":[
            {
                "name": "Amerikansk blanding", 
                "amount": 1,
                "unit": "pose",
                "category": "grønnsaker"
            },
            {
                "name": "Ris",
                "amount": 0,
                "unit": "",
                "category": "annet"
            },
            {
                "name": "Egg",
                "amount": 1,
                "unit": "stk",
                "category": "annet"
            },
            {
                "name": "Soyasaus",
                "amount": 2,
                "unit": "ss",
                "category": "annet"
            },
            {
                "name": "Løk",
                "amount": 1,
                "unit": "stk",
                "category": "grønnsaker"
            },
            {
                "name": "Pølse",
                "amount": 400,
                "unit": "g",
                "category": "kjøtt"
            }
        ]
    },
    {
        "name": "Alt i ett, pølsegryte med pasta",
        "categories": ["Enkel", "Rester", "Pølse"],
        "approach": [
"Mangler."
        ],
        "ingredients":[
            {
                "name": "Pølse",
                "amount": 300,
                "unit": "g",
                "category": "kjøtt"
            },
            {
                "name": "Løk",
                "amount": 1,
                "unit": "stk",
                "category": "grønnsaker"
            },
            {
                "name": "Gulrot",
                "amount": 3,
                "unit": "stk",
                "category": "grønnsaker"
            },
            {
                "name": "Squash",
                "amount": 1,
                "unit": "stk",
                "category": "grønnsaker"
            },
            {
                "name": "Pasta",
                "amount": 150,
                "unit": "g",
                "category": "annet"
            },
            {
                "name": "Spinat",
                "amount": 65,
                "unit": "g",
                "category": "grønnsaker"
            },
            {
                "name": "Buljong",
                "amount": 1,
                "unit": "stk",
                "category": "annet"
            },
            {
                "name": "Hakka tomater",
                "amount": 2,
                "unit": "boks",
                "category": "annet"
            },
            {
                "name": "Matfløte",
                "amount": 1.5,
                "unit": "dl",
                "category": "meieri"
            },
            {
                "name": "Ost",
                "amount": 100,
                "unit": "g",
                "category": "meieri"
            }
        ]
    },
    {
        "name": "Pølse stroganoff",
        "categories": ["Enkel", "Pølse"],
        "approach": [
"Mangler."
        ],
        "ingredients":[
            {
                "name": "Pølse",
                "amount": 500,
                "unit": "g",
                "category": "kjøtt"
            },
            {
                "name": "Ris",
                "amount": 250,
                "unit": "g",
                "category": "annet"
            },
            {
                "name": "Løk",
                "amount": 1,
                "unit": "stk",
                "category": "grønnsaker"
            },
            {
                "name": "Gulrot",
                "amount": 2,
                "unit": "stk",
                "category": "grønnsaker"
            },
            {
                "name": "Paprika",
                "amount": 1,
                "unit": "stk",
                "category": "grønnsaker"
            },
            {
                "name": "Sopp",
                "amount": 150,
                "unit": "g",
                "category": "grønnsaker"
            },
            {
                "name": "Tomatpure",
                "amount": 2,
                "unit": "ss",
                "category": "annet"
            },
            {
                "name": "Hvetemel",
                "amount": 1,
                "unit": "ss",
                "category": "annet"
            },
            {
                "name": "Buljong",
                "amount": 1,
                "unit": "stk",
                "category": "annet"
            },
            {
                "name": "Melk",
                "amount": 2,
                "unit": "dl",
                "category": "meieri"
            },
            {
                "name": "Sukker",
                "amount": 1,
                "unit": "ts",
                "category": "annet"
            }
        ]
    },
    {
        "name": "Meksikansk gatemat",
        "categories": ["Lørdagsmat"],
        "approach": [
"Mangler."
        ],
        "ingredients":[
            {
                "name": "Chorizopølse",
                "amount": 200,
                "unit": "g",
                "category": "kjøtt"
            },
            {
                "name": "Vårløk",
                "amount": 2,
                "unit": "stk",
                "category": "grønnsaker"
            },
            {
                "name": "Ost",
                "amount": 100,
                "unit": "g",
                "category": "meieri"
            },
            {
                "name": "Rømme",
                "amount": 2,
                "unit": "dl",
                "category": "meieri"
            },
            {
                "name": "Tacolefser",
                "amount": 8,
                "unit": "stk",
                "category": "annet"
            },
            {
                "name": "Hvitløk",
                "amount": 2,
                "unit": "fedd",
                "category": "grønnsaker"
            },
            {
                "name": "Chili",
                "amount": 2,
                "unit": "stk",
                "category": "grønnsaker"
            },
            {
                "name": "Rødløk",
                "amount": 1,
                "unit": "stk",
                "category": "grønnsaker"
            },
            {
                "name": "Eddik",
                "amount": 3,
                "unit": "ss",
                "category": "annet"
            },
            {
                "name": "Tomatpure",
                "amount": 1,
                "unit": "ss",
                "category": "annet"
            },
            {
                "name": "Spisskummen",
                "amount": 3,
                "unit": "ts",
                "category": "annet"
            },
            {
                "name": "Chipotlepulver",
                "amount": 2,
                "unit": "ts",
                "category": "annet"
            },
            {
                "name": "Kidneybønner",
                "amount": 1,
                "unit": "boks",
                "category": "annet"
            },
            {
                "name": "Tomat",
                "amount": 2,
                "unit": "stk",
                "category": "grønnsaker"
            },
            {
                "name": "Paprika",
                "amount": 1,
                "unit": "stk",
                "category": "grønnsaker"
            },
            {
                "name": "Sitronsaft",
                "amount": 0,
                "unit": "",
                "category": "annet"
            }
        ]
    },    
    {
        "name": "Vårruller",
        "categories": ["Rester", "Kjøtt", "Asiatisk"],
        "approach": [
"Mangler."
        ],
        "ingredients":[
            {
                "name": "Kjøttdeig",
                "amount": 2,
                "unit": "pakker",
                "category": "kjøtt"
            },
            {
                "name": "Kål",
                "amount": 0.5,
                "unit": "stk",
                "category": "grønnsaker"
            },
            {
                "name": "Gulrot",
                "amount": 2,
                "unit": "stk",
                "category": "grønnsaker"
            },
            {
                "name": "Vårrullkrydder",
                "amount": 3,
                "unit": "ss",
                "category": "annet"
            },
            {
                "name": "Oystersaus",
                "amount": 1,
                "unit": "flaske",
                "category": "annet"
            },
            {
                "name": "Vårrullpapir",
                "amount": 30,
                "unit": "stk",
                "category": "annet"
            },
            {
                "name": "Egg",
                "amount": 1,
                "unit": "stk",
                "category": "annet"
            },
            {
                "name": "Løk",
                "amount": 1,
                "unit": "stk",
                "category": "grønnsaker"
            }
        ]
    },
    {
        "name": "Lasagne",
        "categories": ["Kjøtt", "Lørdagsmat"],
        "approach": [
"Mangler."
        ],
        "ingredients":[
            {
                "name": "Kjøttdeig",
                "amount": 400,
                "unit": "g",
                "category": "kjøtt"
            },
            {
                "name": "Hvitløk",
                "amount": 3,
                "unit": "fedd",
                "category": "grønnsaker"
            },
            {
                "name": "Chili",
                "amount": 1,
                "unit": "stk",
                "category": "grønnsaker"
            },
            {
                "name": "Tomatpure",
                "amount": 200,
                "unit": "g",
                "category": "annet"
            },
            {
                "name": "Hakka tomater",
                "amount": 1,
                "unit": "boks",
                "category": "annet"
            },
            {
                "name": "Løk",
                "amount": 2,
                "unit": "stk",
                "category": "grønnsaker"
            },
            {
                "name": "Gulrot",
                "amount": 1,
                "unit": "stk",
                "category": "grønnsaker"
            },
            {
                "name": "Buljong",
                "amount": 1,
                "unit": "stk",
                "category": "annet"
            },
            {
                "name": "Sukker",
                "amount": 2,
                "unit": "ts",
                "category": "annet"
            },
            {
                "name": "Lasagneplater",
                "amount": 1,
                "unit": "pakke",
                "category": "annet"
            },
            {
                "name": "Ost",
                "amount": 150,
                "unit": "g",
                "category": "meieri"
            },
            {
                "name": "Melk",
                "amount": 7,
                "unit": "dl",
                "category": "meieri"
            },
            {
                "name": "Hvetemel",
                "amount": 60,
                "unit": "g",
                "category": "annet"
            },
            {
                "name": "Smør",
                "amount": 60,
                "unit": "g",
                "category": "meieri"
            }
        ]
    },  
    {
        "name": "Koteletter med bakt søtpotet",
        "categories": ["Kjøtt"],
        "approach": [
"Mangler."
        ],
        "ingredients":[
            {
                "name": "Koteletter",
                "amount": 2,
                "unit": "stk",
                "category": "kjøtt"
            },
            {
                "name": "Søtpotet",
                "amount": 2,
                "unit": "stk",
                "category": "grønnsaker"
            },
            {
                "name": "Kikerter",
                "amount": 1,
                "unit": "boks",
                "category": "annet"
            },
            {
                "name": "Tacokrydder",
                "amount": 1,
                "unit": "pose",
                "category": "annet"
            },
            {
                "name": "Granateple",
                "amount": 1,
                "unit": "stk",
                "category": "grønnsaker"
            },
            {
                "name": "Vårløk",
                "amount": 1,
                "unit": "stk",
                "category": "grønnsaker"
            },
            {
                "name": "Rømme",
                "amount": 2,
                "unit": "ss",
                "category": "meieri"
            }
        ]
    },
    {
        "name": "Ostesuppe",
        "categories": ["Kjøtt", "Suppe"],
        "approach": [
"Mangler."
        ],
        "ingredients":[
            {
                "name": "Smør",
                "amount": 40,
                "unit": "g",
                "category": "meieri"
            },
            {
                "name": "Mel",
                "amount": 40,
                "unit": "g",
                "category": "annet"
            },
            {
                "name": "Melk",
                "amount": 7.5,
                "unit": "dl",
                "category": "meieri"
            },
            {
                "name": "Fløte",
                "amount": 2.5,
                "unit": "dl",
                "category": "meieri"
            },
            {
                "name": "Buljong",
                "amount": 2,
                "unit": "stk",
                "category": "annet"
            },
            {
                "name": "Krydderost",
                "amount": 1,
                "unit": "boks",
                "category": "meieri"
            },
            {
                "name": "Ost",
                "amount": 75,
                "unit": "g",
                "category": "meieri"
            },
            {
                "name": "Kjøttdeig",
                "amount": 400,
                "unit": "g",
                "category": "kjøtt"
            },
            {
                "name": "Løk",
                "amount": 1,
                "unit": "stk",
                "category": "grønnsaker"
            }
        ]
    },
    {
        "name": "Burger med søtpotet fries",
        "categories": ["Kjøtt", "Lørdagsmat"],
        "approach": [
"Mangler."
        ],
        "ingredients":[
            {
                "name": "Kjøttdeig",
                "amount": 400,
                "unit": "g",
                "category": "kjøtt"
            },
            {
                "name": "Bacon",
                "amount": 4,
                "unit": "skiver",
                "category": "kjøtt"
            },
            {
                "name": "Briochebrød",
                "amount": 4,
                "unit": "stk",
                "category": "annet"
            },
            {
                "name": "Salatblader",
                "amount": 0,
                "unit": "",
                "category": "grønnsaker"
            },
            {
                "name": "Tomat",
                "amount": 1,
                "unit": "stk",
                "category": "grønnsaker"
            },
            {
                "name": "Løk",
                "amount": 1.5,
                "unit": "stk",
                "category": "grønnsaker"
            },
            {
                "name": "Honning",
                "amount": 1.5,
                "unit": "ss",
                "category": "annet"
            },
            {
                "name": "Eddik",
                "amount": 3,
                "unit": "ss",
                "category": "annet"
            },
            {
                "name": "Majones",
                "amount": 3,
                "unit": "dl",
                "category": "meieri"
            },
            {
                "name": "Creme fraîche",
                "amount": 2,
                "unit": "ss",
                "category": "meieri"
            },
            {
                "name": "Tomatpure",
                "amount": 2,
                "unit": "ts",
                "category": "annet"
            },
            {
                "name": "Worcester sauce",
                "amount": 1,
                "unit": "ss",
                "category": "annet"
            },
            {
                "name": "Tabasko",
                "amount": 0.5,
                "unit": "ss",
                "category": "annet"
            },
            {
                "name": "Sennep",
                "amount": 1,
                "unit": "ts",
                "category": "annet"
            },
            {
                "name": "Sjalottløk",
                "amount": 1,
                "unit": "stk",
                "category": "grønnsaker"
            },
            {
                "name": "Hvitløk",
                "amount": 1,
                "unit": "fedd",
                "category": "grønnsaker"
            },
            {
                "name": "Sukker",
                "amount": 1,
                "unit": "ts",
                "category": "annet"
            },
            {
                "name": "Søtpotet",
                "amount": 2,
                "unit": "stk",
                "category": "grønnsaker"
            }
        ]
    },
    {
        "name": "Gulrot- og ingefærsuppe",
        "categories": ["Vegetar", "Suppe"],
        "approach": [
"Mangler."
        ],
        "ingredients":[
            {
                "name": "Løk",
                "amount": 1,
                "unit": "liten",
                "category": "grønnsaker"
            },
            {
                "name": "Hvitløk",
                "amount": 1,
                "unit": "fedd",
                "category": "grønnsaker"
            },
            {
                "name": "Olje",
                "amount": 1,
                "unit": "ss",
                "category": "annet"
            },
            {
                "name": "Gulrot",
                "amount": 300,
                "unit": "g",
                "category": "grønnsaker"
            },
            {
                "name": "Ingefær",
                "amount": 1,
                "unit": "ss",
                "category": "grønnsaker"
            },
            {
                "name": "Buljong",
                "amount": 1,
                "unit": "stk",
                "category": "annet"
            },
            {
                "name": "Melk",
                "amount": 0.5,
                "unit": "dl",
                "category": "meieri"
            }
        ]
    },
    {
        "name": "Mangogryte",
        "categories": ["Enkel", "Vegetar"],
        "approach": [
"Mangler."
        ],
        "ingredients":[
            {
                "name": "Kikerter",
                "amount": 1,
                "unit": "boks",
                "category": "annet"
            },
            {
                "name": "Linser",
                "amount": 1,
                "unit": "boks",
                "category": "annet"
            },
            {
                "name": "Hakka tomater",
                "amount": 1,
                "unit": "boks",
                "category": "annet"
            },
            {
                "name": "Løk",
                "amount": 2,
                "unit": "stk",
                "category": "grønnsaker"
            },
            {
                "name": "Hvitløk",
                "amount": 2,
                "unit": "fedd",
                "category": "grønnsaker"
            },
            {
                "name": "Matfløte",
                "amount": 3,
                "unit": "dl",
                "category": "meieri"
            },
            {
                "name": "Melk",
                "amount": 1,
                "unit": "dl",
                "category": "meieri"
            },
            {
                "name": "Mangochutney",
                "amount": 4,
                "unit": "ss",
                "category": "annet"
            },
            {
                "name": "Karri",
                "amount": 3,
                "unit": "ss",
                "category": "annet"
            },
            {
                "name": "Buljong",
                "amount": 1,
                "unit": "stk",
                "category": "annet"
            }
        ]
    },
    {
        "name": "Torleivs chiligryte",
        "categories": ["Enkel", "Suppe"],
        "approach": [
"Mangler."
        ],
        "ingredients":[
            {
                "name": "Olje",
                "amount": 0,
                "unit": "",
                "category": "annet"
            },
            {
                "name": "Buljong",
                "amount": 2,
                "unit": "stk",
                "category": "annet"
            },
            {
                "name": "Løk",
                "amount": 3,
                "unit": "stk",
                "category": "grønnsaker"
            },
            {
                "name": "Hvitløk",
                "amount": 3,
                "unit": "fedd",
                "category": "grønnsaker"
            },
            {
                "name": "Hakka tomater",
                "amount": 2,
                "unit": "boks",
                "category": "annet"
            },
            {
                "name": "Hermetiserte cherrytomater",
                "amount": 1,
                "unit": "boks",
                "category": "annet"
            },
            {
                "name": "Kidneybønner",
                "amount": 1,
                "unit": "boks",
                "category": "annet"
            },
            {
                "name": "Tomatbønner",
                "amount": 1,
                "unit": "boks",
                "category": "annet"
            },
            {
                "name": "Mais",
                "amount": 1,
                "unit": "boks",
                "category": "annet"
            },
            {
                "name": "Cayennepepper",
                "amount": 0,
                "unit": "",
                "category": "annet"
            },
            {
                "name": "Matfløte",
                "amount": 3,
                "unit": "dl",
                "category": "meieri"
            }
        ]
    },
    {
        "name": "Potetsuppe",
        "categories": ["Suppe", "Vegetar"],
        "approach": [
"Mangler."
        ],
        "ingredients":[
            {
                "name": "Poteter",
                "amount": 5,
                "unit": "stk",
                "category": "grønnsaker"
            },
            {
                "name": "Gulrot",
                "amount": 2,
                "unit": "stk",
                "category": "grønnsaker"
            },
            {
                "name": "Hakka tomater",
                "amount": 1,
                "unit": "boks",
                "category": "annet"
            },
            {
                "name": "Linser",
                "amount": 1,
                "unit": "boks",
                "category": "annet"
            },
            {
                "name": "Løk",
                "amount": 1,
                "unit": "stk",
                "category": "grønnsaker"
            },
            {
                "name": "Hvitløk",
                "amount": 1,
                "unit": "fedd",
                "category": "grønnsaker"
            },
            {
                "name": "Tomatpure",
                "amount": 2,
                "unit": "ss",
                "category": "annet"
            },
            {
                "name": "Chili",
                "amount": 1,
                "unit": "stk",
                "category": "grønnsaker"
            },
            {
                "name": "Buljong",
                "amount": 2,
                "unit": "stk",
                "category": "annet"
            }
        ]
    },
    {
        "name": "Linsemoussaka",
        "categories": ["Vegetar"],
        "approach": [
"Mangler."
        ],
        "ingredients":[
            {
                "name": "Løk",
                "amount": 2,
                "unit": "stk",
                "category": "grønnsaker"
            },
            {
                "name": "Hvitløk",
                "amount": 4,
                "unit": "fedd",
                "category": "grønnsaker"
            },
            {
                "name": "Olje",
                "amount": 0,
                "unit": "",
                "category": "annet"
            },
            {
                "name": "Chili",
                "amount": 1,
                "unit": "stk",
                "category": "grønnsaker"
            },
            {
                "name": "Hakka tomater",
                "amount": 2,
                "unit": "boks",
                "category": "annet"
            },
            {
                "name": "Kremfløte",
                "amount": 2,
                "unit": "dl",
                "category": "meieri"
            },
            {
                "name": "Sukker",
                "amount": 0,
                "unit": "",
                "category": "annet"
            },
            {
                "name": "Basilikum",
                "amount": 1,
                "unit": "neve",
                "category": "grønnsaker"
            },
            {
                "name": "Røde linser",
                "amount": 1,
                "unit": "boks",
                "category": "annet"
            },
            {
                "name": "Aubergine",
                "amount": 1,
                "unit": "stk",
                "category": "grønnsaker"
            },
            {
                "name": "Fetaost",
                "amount": 200,
                "unit": "g",
                "category": "meieri"
            },
            {
                "name": "Spinat",
                "amount": 300,
                "unit": "g",
                "category": "grønnsaker"
            },
            {
                "name": "Ost",
                "amount": 200,
                "unit": "g",
                "category": "meieri"
            }
        ]
    },
    {
        "name": "Sopp- og baconstuing",
        "categories": ["Tilbehør"],
        "approach": [
"Mangler."
        ],
        "ingredients":[
            {
                "name": "Bacon",
                "amount": 200,
                "unit": "g",
                "category": "kjøtt"
            },
            {
                "name": "Sjampinjong",
                "amount": 250,
                "unit": "g",
                "category": "grønnsaker"
            },
            {
                "name": "Rømme",
                "amount": 5,
                "unit": "ss",
                "category": "meieri"
            },
            {
                "name": "Basilikum",
                "amount": 1,
                "unit": "ts",
                "category": "grønnsaker"
            },
            {
                "name": "Persille",
                "amount": 1,
                "unit": "ss",
                "category": "grønnsaker"
            }
        ]
    },
    {
        "name": "Fiskeboller i hvit saus",
        "categories": ["Fisk", "Enkel"],
        "approach": [
"Mangler."
        ],
        "ingredients":[
            {
                "name": "Fiskeboller",
                "amount": 1,
                "unit": "boks",
                "category": "annet"
            },
            {
                "name": "Gulrot",
                "amount": 4,
                "unit": "stk",
                "category": "grønnsaker"
            },
            {
                "name": "Poteter",
                "amount": 5,
                "unit": "stk",
                "category": "grønnsaker"
            },
            {
                "name": "Melk",
                "amount": 4,
                "unit": "dl",
                "category": "meieri"
            },
            {
                "name": "Hvetemel",
                "amount": 3,
                "unit": "ss",
                "category": "annet"
            },
            {
                "name": "Smør",
                "amount": 2,
                "unit": "ss",
                "category": "meieri"
            }
        ]
    },
    {
        "name": "Taco",
        "categories": ["Lørdagsmat", "Kjøtt"],
        "approach": [
"Mangler."
        ],
        "ingredients":[
            {
                "name": "Kjøttdeig",
                "amount": 400,
                "unit": "g",
                "category": "kjøtt"
            },
            {
                "name": "Tacokrydder",
                "amount": 1,
                "unit": "pose",
                "category": "annet"
            },
            {
                "name": "Taco lefser",
                "amount": 1,
                "unit": "pakke",
                "category": "annet"
            },
            {
                "name": "Salat",
                "amount": 0,
                "unit": "",
                "category": "grønnsaker"
            },
            {
                "name": "Tomat",
                "amount": 2,
                "unit": "stk",
                "category": "grønnsaker"
            },
            {
                "name": "Rømme",
                "amount": 2,
                "unit": "dl",
                "category": "meieri"
            },
            {
                "name": "Ost",
                "amount": 100,
                "unit": "g",
                "category": "meieri"
            },
            {
                "name": "Agurk",
                "amount": 0.5,
                "unit": "stk",
                "category": "grønnsaker"
            },
            {
                "name": "Paprika",
                "amount": 1,
                "unit": "stk",
                "category": "grønnsaker"
            },
            {
                "name": "Tacosaus",
                "amount": 1,
                "unit": "glass",
                "category": "annet"
            },
            {
                "name": "Avokado",
                "amount": 1,
                "unit": "stk",
                "category": "grønnsaker"
            },
            {
                "name": "Nachoschips",
                "amount": 0.5,
                "unit": "pose",
                "category": "annet"
            }
        ]
    }
]